README
setup.py
tkwriter.py
tkwriter.egg-info/PKG-INFO
tkwriter.egg-info/SOURCES.txt
tkwriter.egg-info/dependency_links.txt
tkwriter.egg-info/entry_points.txt
tkwriter.egg-info/top_level.txt