Metadata-Version: 1.1
Name: tkwriter
Version: 1.0.1
Summary: A GUI text editor using tkinter
Home-page: https://github.com/pypa/sampleproject
Author: dot bit
Author-email: dotbit@xx.xx
License: UNKNOWN
Keywords: tkinter editor GUI text
Platform: UNKNOWN
Classifier: Programming Language :: Python :: 3.6
